{"nodes": [{"id": "c_projecto_hotel_chipre_pms_frontend_src_api_rooms_ts", "label": "rooms.ts", "file_type": "code", "source_file": "C:\\PROJECTO\\Hotel-Chipre-PMS\\frontend\\src\\api\\rooms.ts", "source_location": "L1"}, {"id": "rooms_listrooms", "label": "listRooms()", "file_type": "code", "source_file": "C:\\PROJECTO\\Hotel-Chipre-PMS\\frontend\\src\\api\\rooms.ts", "source_location": "L26"}, {"id": "rooms_listroomcategories", "label": "listRoomCategories()", "file_type": "code", "source_file": "C:\\PROJECTO\\Hotel-Chipre-PMS\\frontend\\src\\api\\rooms.ts", "source_location": "L28"}, {"id": "rooms_createroomcategory", "label": "createRoomCategory()", "file_type": "code", "source_file": "C:\\PROJECTO\\Hotel-Chipre-PMS\\frontend\\src\\api\\rooms.ts", "source_location": "L31"}, {"id": "rooms_updateroomcategory", "label": "updateRoomCategory()", "file_type": "code", "source_file": "C:\\PROJECTO\\Hotel-Chipre-PMS\\frontend\\src\\api\\rooms.ts", "source_location": "L34"}, {"id": "rooms_createroom", "label": "createRoom()", "file_type": "code", "source_file": "C:\\PROJECTO\\Hotel-Chipre-PMS\\frontend\\src\\api\\rooms.ts", "source_location": "L40"}, {"id": "rooms_updateroom", "label": "updateRoom()", "file_type": "code", "source_file": "C:\\PROJECTO\\Hotel-Chipre-PMS\\frontend\\src\\api\\rooms.ts", "source_location": "L45"}, {"id": "rooms_updateroomstatus", "label": "updateRoomStatus()", "file_type": "code", "source_file": "C:\\PROJECTO\\Hotel-Chipre-PMS\\frontend\\src\\api\\rooms.ts", "source_location": "L51"}, {"id": "rooms_checkroomavailability", "label": "checkRoomAvailability()", "file_type": "code", "source_file": "C:\\PROJECTO\\Hotel-Chipre-PMS\\frontend\\src\\api\\rooms.ts", "source_location": "L70"}], "edges": [{"source": "c_projecto_hotel_chipre_pms_frontend_src_api_rooms_ts", "target": "c_projecto_hotel_chipre_pms_frontend_src_api_client", "relation": "imports_from", "confidence": "EXTRACTED", "source_file": "C:\\PROJECTO\\Hotel-Chipre-PMS\\frontend\\src\\api\\rooms.ts", "source_location": "L1", "weight": 1.0}, {"source": "c_projecto_hotel_chipre_pms_frontend_src_api_rooms_ts", "target": "rooms_listrooms", "relation": "contains", "confidence": "EXTRACTED", "source_file": "C:\\PROJECTO\\Hotel-Chipre-PMS\\frontend\\src\\api\\rooms.ts", "source_location": "L26", "weight": 1.0}, {"source": "c_projecto_hotel_chipre_pms_frontend_src_api_rooms_ts", "target": "rooms_listroomcategories", "relation": "contains", "confidence": "EXTRACTED", "source_file": "C:\\PROJECTO\\Hotel-Chipre-PMS\\frontend\\src\\api\\rooms.ts", "source_location": "L28", "weight": 1.0}, {"source": "c_projecto_hotel_chipre_pms_frontend_src_api_rooms_ts", "target": "rooms_createroomcategory", "relation": "contains", "confidence": "EXTRACTED", "source_file": "C:\\PROJECTO\\Hotel-Chipre-PMS\\frontend\\src\\api\\rooms.ts", "source_location": "L31", "weight": 1.0}, {"source": "c_projecto_hotel_chipre_pms_frontend_src_api_rooms_ts", "target": "rooms_updateroomcategory", "relation": "contains", "confidence": "EXTRACTED", "source_file": "C:\\PROJECTO\\Hotel-Chipre-PMS\\frontend\\src\\api\\rooms.ts", "source_location": "L34", "weight": 1.0}, {"source": "c_projecto_hotel_chipre_pms_frontend_src_api_rooms_ts", "target": "rooms_createroom", "relation": "contains", "confidence": "EXTRACTED", "source_file": "C:\\PROJECTO\\Hotel-Chipre-PMS\\frontend\\src\\api\\rooms.ts", "source_location": "L40", "weight": 1.0}, {"source": "c_projecto_hotel_chipre_pms_frontend_src_api_rooms_ts", "target": "rooms_updateroom", "relation": "contains", "confidence": "EXTRACTED", "source_file": "C:\\PROJECTO\\Hotel-Chipre-PMS\\frontend\\src\\api\\rooms.ts", "source_location": "L45", "weight": 1.0}, {"source": "c_projecto_hotel_chipre_pms_frontend_src_api_rooms_ts", "target": "rooms_updateroomstatus", "relation": "contains", "confidence": "EXTRACTED", "source_file": "C:\\PROJECTO\\Hotel-Chipre-PMS\\frontend\\src\\api\\rooms.ts", "source_location": "L51", "weight": 1.0}, {"source": "c_projecto_hotel_chipre_pms_frontend_src_api_rooms_ts", "target": "rooms_checkroomavailability", "relation": "contains", "confidence": "EXTRACTED", "source_file": "C:\\PROJECTO\\Hotel-Chipre-PMS\\frontend\\src\\api\\rooms.ts", "source_location": "L70", "weight": 1.0}], "raw_calls": [{"caller_nid": "rooms_listrooms", "callee": "apiFetch", "source_file": "C:\\PROJECTO\\Hotel-Chipre-PMS\\frontend\\src\\api\\rooms.ts", "source_location": "L26"}, {"caller_nid": "rooms_listroomcategories", "callee": "apiFetch", "source_file": "C:\\PROJECTO\\Hotel-Chipre-PMS\\frontend\\src\\api\\rooms.ts", "source_location": "L29"}, {"caller_nid": "rooms_createroomcategory", "callee": "apiFetch", "source_file": "C:\\PROJECTO\\Hotel-Chipre-PMS\\frontend\\src\\api\\rooms.ts", "source_location": "L32"}, {"caller_nid": "rooms_updateroomcategory", "callee": "apiFetch", "source_file": "C:\\PROJECTO\\Hotel-Chipre-PMS\\frontend\\src\\api\\rooms.ts", "source_location": "L38"}, {"caller_nid": "rooms_createroom", "callee": "apiFetch", "source_file": "C:\\PROJECTO\\Hotel-Chipre-PMS\\frontend\\src\\api\\rooms.ts", "source_location": "L43"}, {"caller_nid": "rooms_updateroom", "callee": "apiFetch", "source_file": "C:\\PROJECTO\\Hotel-Chipre-PMS\\frontend\\src\\api\\rooms.ts", "source_location": "L49"}, {"caller_nid": "rooms_updateroomstatus", "callee": "apiFetch", "source_file": "C:\\PROJECTO\\Hotel-Chipre-PMS\\frontend\\src\\api\\rooms.ts", "source_location": "L52"}, {"caller_nid": "rooms_checkroomavailability", "callee": "String", "source_file": "C:\\PROJECTO\\Hotel-Chipre-PMS\\frontend\\src\\api\\rooms.ts", "source_location": "L75"}, {"caller_nid": "rooms_checkroomavailability", "callee": "apiFetch", "source_file": "C:\\PROJECTO\\Hotel-Chipre-PMS\\frontend\\src\\api\\rooms.ts", "source_location": "L79"}, {"caller_nid": "rooms_checkroomavailability", "callee": "toString", "source_file": "C:\\PROJECTO\\Hotel-Chipre-PMS\\frontend\\src\\api\\rooms.ts", "source_location": "L79"}]}