{"nodes": [{"id": "app_middleware_subscription_py", "label": "subscription.py", "file_type": "code", "source_file": "app\\middleware\\subscription.py", "source_location": "L1"}, {"id": "subscription_subscriptionenforcementmiddleware", "label": "SubscriptionEnforcementMiddleware", "file_type": "code", "source_file": "app\\middleware\\subscription.py", "source_location": "L13"}, {"id": "subscription_subscriptionenforcementmiddleware_init", "label": ".__init__()", "file_type": "code", "source_file": "app\\middleware\\subscription.py", "source_location": "L14"}, {"id": "subscription_subscriptionenforcementmiddleware_call", "label": ".__call__()", "file_type": "code", "source_file": "app\\middleware\\subscription.py", "source_location": "L17"}, {"id": "subscription_rationale_1", "label": "Middleware to block mutating requests when subscription enforcement is enabled.", "file_type": "rationale", "source_file": "app\\middleware\\subscription.py", "source_location": "L1"}], "edges": [{"source": "app_middleware_subscription_py", "target": "fastapi", "relation": "imports_from", "confidence": "EXTRACTED", "source_file": "app\\middleware\\subscription.py", "source_location": "L5", "weight": 1.0}, {"source": "app_middleware_subscription_py", "target": "fastapi_responses", "relation": "imports_from", "confidence": "EXTRACTED", "source_file": "app\\middleware\\subscription.py", "source_location": "L6", "weight": 1.0}, {"source": "app_middleware_subscription_py", "target": "app_config", "relation": "imports_from", "confidence": "EXTRACTED", "source_file": "app\\middleware\\subscription.py", "source_location": "L8", "weight": 1.0}, {"source": "app_middleware_subscription_py", "target": "app_database", "relation": "imports_from", "confidence": "EXTRACTED", "source_file": "app\\middleware\\subscription.py", "source_location": "L9", "weight": 1.0}, {"source": "app_middleware_subscription_py", "target": "app_services_subscription_entitlements", "relation": "imports_from", "confidence": "EXTRACTED", "source_file": "app\\middleware\\subscription.py", "source_location": "L10", "weight": 1.0}, {"source": "app_middleware_subscription_py", "target": "subscription_subscriptionenforcementmiddleware", "relation": "contains", "confidence": "EXTRACTED", "source_file": "app\\middleware\\subscription.py", "source_location": "L13", "weight": 1.0}, {"source": "subscription_subscriptionenforcementmiddleware", "target": "subscription_subscriptionenforcementmiddleware_init", "relation": "method", "confidence": "EXTRACTED", "source_file": "app\\middleware\\subscription.py", "source_location": "L14", "weight": 1.0}, {"source": "subscription_subscriptionenforcementmiddleware", "target": "subscription_subscriptionenforcementmiddleware_call", "relation": "method", "confidence": "EXTRACTED", "source_file": "app\\middleware\\subscription.py", "source_location": "L17", "weight": 1.0}, {"source": "subscription_rationale_1", "target": "app_middleware_subscription_py", "relation": "rationale_for", "confidence": "EXTRACTED", "source_file": "app\\middleware\\subscription.py", "source_location": "L1", "weight": 1.0}]}